PersonalLibrary/Initial.py
PersonalLibrary/__init__.py
PersonalLibrary/Config/Config.py
PersonalLibrary/Config/__init__.py
PersonalLibrary/EasyFlask/EasyFlask.py
PersonalLibrary/EasyFlask/HtmlWriter.py
PersonalLibrary/EasyFlask/__init__.py
PersonalLibrary/EasyHtmlProgress/EasyHtmlProgress.py
PersonalLibrary/EasyHtmlProgress/Tags.py
PersonalLibrary/EasyHtmlProgress/__init__.py
PersonalLibrary/EasyRequest/EasyRequest.py
PersonalLibrary/EasyRequest/__init__.py
PersonalLibrary/EasySQL/EasySQL.py
PersonalLibrary/EasySQL/FieldType.py
PersonalLibrary/EasySQL/__init__.py
PersonalLibrary/EasyTkinter/CanvasFunction.py
PersonalLibrary/EasyTkinter/Controllers.py
PersonalLibrary/EasyTkinter/EasySystemTray.py
PersonalLibrary/EasyTkinter/EasyTkinter.py
PersonalLibrary/EasyTkinter/__init__.py
PersonalLibrary/LibraryException/AccountException.py
PersonalLibrary/LibraryException/ConfigOptionException.py
PersonalLibrary/LibraryException/ConnectionExption.py
PersonalLibrary/LibraryException/FlaskMethodException.py
PersonalLibrary/LibraryException/LibraryException.py
PersonalLibrary/LibraryException/NoneFileContextException.py
PersonalLibrary/LibraryException/__init__.py
PersonalLibrary/LibraryLogger/LibraryLogger.py
PersonalLibrary/LibraryLogger/__init__.py
PersonalLibrary/Text/Colors.py
PersonalLibrary/Text/Text.py
PersonalLibrary/Text/__init__.py
PersonalLibrary/Text/lang_for_zn_cn.py
PersonalLibrary-1.2.3.dist-info/LICENSE
PersonalLibrary-1.2.3.dist-info/METADATA
PersonalLibrary-1.2.3.dist-info/WHEEL
PersonalLibrary-1.2.3.dist-info/top_level.txt
PersonalLibrary-1.2.3.dist-info/RECORD
