Metadata-Version: 2.1
Name: PersonalLibrary
Version: 1.2.3
Summary: A collection of libraries or packages that are commonly used by some individuals
Home-page: https://gitee.com/XichengWu/personal-library
Author: XichengWu
Author-email: mcht1023@gmail.com
License-File: LICENSE
